qmotion_qsync/__init__.py
qmotion_qsync/const.py
qmotion_qsync/exceptions.py
qmotion_qsync/position.py
qmotion_qsync-0.1.0.dist-info/LICENSE
qmotion_qsync-0.1.0.dist-info/METADATA
qmotion_qsync-0.1.0.dist-info/WHEEL
qmotion_qsync-0.1.0.dist-info/top_level.txt
qmotion_qsync-0.1.0.dist-info/RECORD
