Metadata-Version: 2.1
Name: qmotion-qsync
Version: 0.1.0
Summary: Control Qmotion Gen2 shades using Qsync device
Home-page: https://github.com/tmoran3020/qmotion-qsync
Author: Tim Moran
License: MIT
Keywords: qmotion,qsync
Platform: UNKNOWN
Classifier: License :: OSI Approved :: MIT License
Classifier: Programming Language :: Python :: 3
License-File: LICENSE
